{
  "variants": {
    "type=north": {
      "model": "songe:block/roof_tile_stalagnate_vertical_slab", "y": 0, "uvlock": true
    },
    "type=south": {
      "model": "songe:block/roof_tile_stalagnate_vertical_slab", "y": 180, "uvlock": true
    },
    "type=east": {
      "model": "songe:block/roof_tile_stalagnate_vertical_slab", "y": 90, "uvlock": true
    },
    "type=west": {
      "model": "songe:block/roof_tile_stalagnate_vertical_slab", "y": 270, "uvlock": true
    },
    "type=double": {
      "model": "betternether:block/roof_tile_stalagnate" }
  }
}
